swimlane_platform/__init__.py
swimlane_platform/add_file_encryption_key.py
swimlane_platform/install.py
swimlane_platform/upgrade.py
swimlane_platform/wizard.py
swimlane_platform/backup/__init__.py
swimlane_platform/backup/backup.py
swimlane_platform/backup/backup_restore_base.py
swimlane_platform/backup/restore.py
swimlane_platform/install_steps/__init__.py
swimlane_platform/install_steps/enable_web_ssl.py
swimlane_platform/install_steps/pre_flight_check.py
swimlane_platform/install_steps/set_permissions.py
swimlane_platform/install_steps/setup_dbs.py
swimlane_platform/install_steps/setup_swimlane_environment.py
swimlane_platform/lib/__init__.py
swimlane_platform/lib/args_config_questions.py
swimlane_platform/lib/base_with_log.py
swimlane_platform/lib/constants.py
swimlane_platform/lib/db_configuration.py
swimlane_platform/lib/debug_decorators.py
swimlane_platform/lib/docker_compose_file_manager.py
swimlane_platform/lib/docker_compose_manager.py
swimlane_platform/lib/docker_image.py
swimlane_platform/lib/docker_manager.py
swimlane_platform/lib/env_manager.py
swimlane_platform/lib/expected_exceptions.py
swimlane_platform/lib/functions.py
swimlane_platform/lib/logger.py
swimlane_platform/lib/models.py
swimlane_platform/lib/mongo_manager.py
swimlane_platform/lib/names.py
swimlane_platform/lib/open_ssl_manager.py
swimlane_platform/lib/os_manager.py
swimlane_platform/lib/questions_groups.py
swimlane_platform/lib/version_manager.py
swimlane_platform/shared_steps/__init__.py
swimlane_platform/shared_steps/enable_mongo_ssl.py
swimlane_platform/shared_steps/enable_turbine.py
swimlane_platform/shared_steps/set_mongo_tls_flags.py
swimlane_platform/upgrade_steps/__init__.py
swimlane_platform/upgrade_steps/upgrade_from_1000_1001.py
swimlane_platform/upgrade_steps/upgrade_from_1001_1002.py
swimlane_platform/upgrade_steps/upgrade_from_1002_1010.py
swimlane_platform/upgrade_steps/upgrade_from_1010_1011.py
swimlane_platform/upgrade_steps/upgrade_from_1011_1012.py
swimlane_platform-10.6.0.dist-info/METADATA
swimlane_platform-10.6.0.dist-info/WHEEL
swimlane_platform-10.6.0.dist-info/entry_points.txt
swimlane_platform-10.6.0.dist-info/top_level.txt
swimlane_platform-10.6.0.dist-info/RECORD
