Metadata-Version: 2.1
Name: swimlane-platform
Version: 10.6.0
Summary: Swimlane platform on linux. Install, Upgrade, Backups etc. All maintenance.
Home-page: https://swimlane.com/knowledge-center/install/Swimlane_Linux_Toolkit_Installer/
Author: Swimlane
Author-email: info@swimlane.com
License: UNKNOWN
Platform: UNKNOWN
Classifier: Programming Language :: Python
Classifier: Programming Language :: Python :: 2.7
Classifier: Programming Language :: Python :: 3.6
Requires-Dist: PyYAML (==5.4)
Requires-Dist: pyfiglet (>=0.8.0)
Requires-Dist: Pygments (==2.5.2)
Requires-Dist: PyInquirer (==1.0.3)
Requires-Dist: docker (==4.0.2)
Requires-Dist: future (==0.17.1)
Requires-Dist: typing (==3.7.4)
Requires-Dist: pymongo (==3.8.0)
Requires-Dist: cryptography (==3.3)
Requires-Dist: pyOpenSSL (==20.0.0)
Requires-Dist: semver (==2.8.1)
Requires-Dist: distro (==1.4.0)
Requires-Dist: semantic-version (==2.6.0)
Requires-Dist: validators (==0.14.0)
